luks_tray/History.py
luks_tray/IniTool.py
luks_tray/Utils.py
luks_tray/__init__.py
luks_tray/main.py
luks_tray/resources/alert-shield-v04.svg
luks_tray/resources/green-shield-v04.svg
luks_tray/resources/orange-shield-v04.svg
luks_tray/resources/white-shield-v04.svg
luks_tray/resources/yellow-shield-v04.svg
luks_tray-2.0.5.dist-info/entry_points.txt
luks_tray-2.0.5.dist-info/licenses/LICENSE
luks_tray-2.0.5.dist-info/WHEEL
luks_tray-2.0.5.dist-info/METADATA
luks_tray-2.0.5.dist-info/RECORD
