Metadata-Version: 2.4
Name: luks-tray
Version: 2.0.5
Summary: A Qt-based tray app for managing LUKS encrypted volumes
Keywords: LUKS,Qt6,applet,tray
Author-email: Joe Defen <joedef@gmail.com>
Requires-Python: >=3.8
Classifier: Programming Language :: Python :: 3
Classifier: License :: OSI Approved :: MIT License
Classifier: Operating System :: POSIX :: Linux
License-File: LICENSE
Requires-Dist: psutil
Requires-Dist: PyQt6
Requires-Dist: cryptography
Requires-Dist: petname
Project-URL: Bug Tracker, https://github.com/joedefen/luks-tray/issues
Project-URL: Homepage, https://github.com/joedefen/luks-tray
